Workbook

Sheet attributes
A1: Asset ID | B1: Asset Name | C1: Asset Attribute 1 | D1: Asset Attribute 2
A2: ZAPAN | B2: PAN AFRICAN RESOURCES PLC | C2: Resources | D2: Materials
A3: ZAMNP | B3: MONDI PLC | C3: Rand Sensitives | D3: Materials
A4: ZABTI | B4: BRITISH AMERICAN TOBACCO PLC | C4: Rand Sensitives | D4: Consumer Staples
A5: ZAINP | B5: INVESTEC PLC | C5: Rand Sensitives | D5: Financials
A6: ZACFR | B6: COMPAGNIE FINANCIERE RICHEMONT SA | C6: Rand Sensitives | D6: Consumer Discretionary
A7: ZAATT | B7: ATTACQ LTD | C7: Property | D7: Real Estate
A8: ZACOH | B8: CURRO HOLDINGS LTD | C8: SA Inc | D8: Consumer Discretionary
A9: ZAAGL | B9: ANGLO AMERICAN PLC | C9: Resources | D9: Materials
A10: ZALHC | B10: LIFE HEALTHCARE GROUP HOLDINGS LTD | C10: SA Inc | D10: Health Care
A11: ZAVOD | B11: VODACOM GROUP LTD | C11: SA Inc | D11: Communication Services
A12: ZAAIP | B12: ADCOCK INGRAM HOLDINGS LTD | C12: SA Inc | D12: Health Care
... A77: ZAARI | B77: AFRICAN RAINBOW MINERALS LTD | C77: Resources | D77: Materials

Sheet funds_20231231
A1: Fund A | E1: Fund B
A2: Asset ID | B2: Holdings | E2: Asset ID | F2: Holdings
A3: ZAMNP | B3: 205985 | E3: ZAMNP | F3: 215985
A4: ZABTI | B4: 143860 | E4: ZABTI | F4: 153860
A5: ZAINP | B5: 350025 | E5: ZAINP | F5: 360025
A6: ZACFR | B6: 369 | E6: ZACFR | F6: 10369
A7: ZAATT | B7: 1086 | E7: ZAATT | F7: 11086
A8: ZAAGL | B8: 176573 | E8: ZAAGL | F8: 186573
A9: ZALHC | B9: 922 | E9: ZALHC | F9: 10922
A10: ZAVOD | B10: 178090 | E10: ZAVOD | F10: 188090
A11: ZARBX | B11: 1774 | E11: ZARBX | F11: 11774
A12: ZAEXX | B12: 154023 | E12: ZAEXX | F12: 164023
A13: ZASPP | B13: 293 | E13: ZASPP | F13: 10293
A14: ZAVKE | B14: 1515 | E14: ZAVKE | F14: 11515
... A48: ZAARI | B48: 86807 | E48: ZAARI | F48: 96807

Sheet benchmark
A1: Asset ID | B1: Holdings | C1: Mkt Value | D1: Price | E1: Date
A2: ZAPAN | B2: 2.8308205e+08 | C2: 3.2838014e+08 | D2: 0.213868 | E2: 41639
A3: ZAMNP | B3: 1.5791355e+08 | C3: 2.7318158e+09 | D3: 17.299439 | E3: 41639
A4: ZABTI | B4: 3.0389436e+08 | C4: 1.6252092e+10 | D4: 53.479413 | E4: 41639
A5: ZAINP | B5: 3.4504301e+08 | C5: 2.4895477e+09 | D5: 7.2151808 | E5: 41639
A6: ZACFR | B6: 1148400000 | C6: 1.1466731e+10 | D6: 9.9849624 | E6: 41639
A7: ZAATT | B7: 3.6881762e+08 | C7: 6.2680068e+08 | D7: 1.6994868 | E7: 41639
A8: ZACOH | B8: 56010934 | C8: 1.4866728e+08 | D8: 2.6542547 | E8: 41639
A9: ZAAGL | B9: 7.0272747e+08 | C9: 1.5364563e+10 | D9: 21.864184 | E9: 41639
A10: ZALHC | B10: 917144580 | C10: 3.6655135e+09 | D10: 3.9966583 | E10: 41639
A11: ZAVOD | B11: 327349880 | C11: 4.1568239e+09 | D11: 12.698413 | E11: 41639
A12: ZAAIP | B12: 1.4810124e+08 | C12: 1.0025423e+09 | D12: 6.7693042 | E12: 41639
A13: ZABLU | B13: 3.7097997e+08 | C13: 3.010698e+08 | D13: 0.81155269 | E13: 41639
... A77: ZAARI | B77: 77579841 | C77: 1.399937e+09 | D77: 18.045113 | E77: 41639

Sheet prices
A1: Asset ID | B1: Price | C1: Date
A2: ZAPAN | B2: 0.213868 | C2: 41639
A3: ZAMNP | B3: 17.299439 | C3: 41639
A4: ZABTI | B4: 53.479413 | C4: 41639
A5: ZAINP | B5: 7.2151808 | C5: 41639
A6: ZACFR | B6: 9.9849624 | C6: 41639
A7: ZAATT | B7: 1.6994868 | C7: 41639
A8: ZACOH | B8: 2.6542547 | C8: 41639
A9: ZAAGL | B9: 21.864184 | C9: 41639
A10: ZALHC | B10: 3.9966583 | C10: 41639
A11: ZAVOD | B11: 12.698413 | C11: 41639
A12: ZAAIP | B12: 6.7693042 | C12: 41639
A13: ZABLU | B13: 0.81155269 | C13: 41639
... A10019: ZAARI | B10019: 7.9697933 | C10019: 45657

Sheet 1_marketValue
A1: Asset ID | B1: Holdings | C1: Price_2023_12_31 | D1: Market Value | E1: Weight | F1: Annual Return | G1: Attribute
A2: =funds_20231231!A3 -> ZAMNP | B2: =funds_20231231!B3 -> 205985 | C2: {=_xlfn.XLOOKUP(1, (prices!$A:$A=A2)*(prices!$C:$C=DATE(2023,12,31)), prices!$B:$B)} -> 19.849624 | D2: =B2*C2 -> 4088724.8 | E2: =D2/$D$49 -> 0.029466683 | F2: {=(_xlfn.XLOOKUP(1, (prices!$A:$A=A2)*(prices!$C:$C=DATE(2024,12,31)), prices!$B:$B)/_xlfn.XLOOKUP(1, (prices!$A:$A=A2)*(prices!$C:$C=DATE(2023,12,31)), prices!$B:$B))-1} -> -0.25913547 | G2: =_xlfn.XLOOKUP(A2, attributes!A:A, attributes!C:C, "N/A") -> Rand Sensitives
A3: =funds_20231231!A4 -> ZABTI | B3: =funds_20231231!B4 -> 143860 | C3: {=_xlfn.XLOOKUP(1, (prices!$A:$A=A3)*(prices!$C:$C=DATE(2023,12,31)), prices!$B:$B)} -> 29.610936 | D3: =B3*C3 -> 4259829.3 | E3: =D3/$D$49 -> 0.030699802 | F3: {=(_xlfn.XLOOKUP(1, (prices!$A:$A=A3)*(prices!$C:$C=DATE(2024,12,31)), prices!$B:$B)/_xlfn.XLOOKUP(1, (prices!$A:$A=A3)*(prices!$C:$C=DATE(2023,12,31)), prices!$B:$B))-1} -> 0.2108454 | G3: =_xlfn.XLOOKUP(A3, attributes!A:A, attributes!C:C, "N/A") -> Rand Sensitives
A4: =funds_20231231!A5 -> ZAINP | B4: =funds_20231231!B5 -> 350025 | C4: {=_xlfn.XLOOKUP(1, (prices!$A:$A=A4)*(prices!$C:$C=DATE(2023,12,31)), prices!$B:$B)} -> 6.887218 | D4: =B4*C4 -> 2410698.5 | E4: =D4/$D$49 -> 0.017373458 | F4: {=(_xlfn.XLOOKUP(1, (prices!$A:$A=A4)*(prices!$C:$C=DATE(2024,12,31)), prices!$B:$B)/_xlfn.XLOOKUP(1, (prices!$A:$A=A4)*(prices!$C:$C=DATE(2023,12,31)), prices!$B:$B))-1} -> -0.025098178 | G4: =_xlfn.XLOOKUP(A4, attributes!A:A, attributes!C:C, "N/A") -> Rand Sensitives
A5: =funds_20231231!A6 -> ZACFR | B5: =funds_20231231!B6 -> 369 | C5: {=_xlfn.XLOOKUP(1, (prices!$A:$A=A5)*(prices!$C:$C=DATE(2023,12,31)), prices!$B:$B)} -> 140.40246 | D5: =B5*C5 -> 51808.508 | E5: =D5/$D$49 -> 0.00037337433 | F5: {=(_xlfn.XLOOKUP(1, (prices!$A:$A=A5)*(prices!$C:$C=DATE(2024,12,31)), prices!$B:$B)/_xlfn.XLOOKUP(1, (prices!$A:$A=A5)*(prices!$C:$C=DATE(2023,12,31)), prices!$B:$B))-1} -> 0.047748861 | G5: =_xlfn.XLOOKUP(A5, attributes!A:A, attributes!C:C, "N/A") -> Rand Sensitives
A6: =funds_20231231!A7 -> ZAATT | B6: =funds_20231231!B7 -> 1086 | C6: {=_xlfn.XLOOKUP(1, (prices!$A:$A=A6)*(prices!$C:$C=DATE(2023,12,31)), prices!$B:$B)} -> 0.50416951 | D6: =B6*C6 -> 547.52809 | E6: =D6/$D$49 -> 3.9459337e-06 | F6: {=(_xlfn.XLOOKUP(1, (prices!$A:$A=A6)*(prices!$C:$C=DATE(2024,12,31)), prices!$B:$B)/_xlfn.XLOOKUP(1, (prices!$A:$A=A6)*(prices!$C:$C=DATE(2023,12,31)), prices!$B:$B))-1} -> 0.45790082 | G6: =_xlfn.XLOOKUP(A6, attributes!A:A, attributes!C:C, "N/A") -> Property
A7: =funds_20231231!A8 -> ZAAGL | B7: =funds_20231231!B8 -> 176573 | C7: {=_xlfn.XLOOKUP(1, (prices!$A:$A=A7)*(prices!$C:$C=DATE(2023,12,31)), prices!$B:$B)} -> 25.891456 | D7: =B7*C7 -> 4571732 | E7: =D7/$D$49 -> 0.032947627 | F7: {=(_xlfn.XLOOKUP(1, (prices!$A:$A=A7)*(prices!$C:$C=DATE(2024,12,31)), prices!$B:$B)/_xlfn.XLOOKUP(1, (prices!$A:$A=A7)*(prices!$C:$C=DATE(2023,12,31)), prices!$B:$B))-1} -> 0.12951675 | G7: =_xlfn.XLOOKUP(A7, attributes!A:A, attributes!C:C, "N/A") -> Resources
A8: =funds_20231231!A9 -> ZALHC | B8: =funds_20231231!B9 -> 922 | C8: {=_xlfn.XLOOKUP(1, (prices!$A:$A=A8)*(prices!$C:$C=DATE(2023,12,31)), prices!$B:$B)} -> 1.0045113 | D8: =B8*C8 -> 926.1594 | E8: =D8/$D$49 -> 6.6746594e-06 | F8: {=(_xlfn.XLOOKUP(1, (prices!$A:$A=A8)*(prices!$C:$C=DATE(2024,12,31)), prices!$B:$B)/_xlfn.XLOOKUP(1, (prices!$A:$A=A8)*(prices!$C:$C=DATE(2023,12,31)), prices!$B:$B))-1} -> -0.13585389 | G8: =_xlfn.XLOOKUP(A8, attributes!A:A, attributes!C:C, "N/A") -> SA Inc
A9: =funds_20231231!A10 -> ZAVOD | B9: =funds_20231231!B10 -> 178090 | C9: {=_xlfn.XLOOKUP(1, (prices!$A:$A=A9)*(prices!$C:$C=DATE(2023,12,31)), prices!$B:$B)} -> 5.796309 | D9: =B9*C9 -> 1032264.7 | E9: =D9/$D$49 -> 0.0074393404 | F9: {=(_xlfn.XLOOKUP(1, (prices!$A:$A=A9)*(prices!$C:$C=DATE(2024,12,31)), prices!$B:$B)/_xlfn.XLOOKUP(1, (prices!$A:$A=A9)*(prices!$C:$C=DATE(2023,12,31)), prices!$B:$B))-1} -> -0.073291438 | G9: =_xlfn.XLOOKUP(A9, attributes!A:A, attributes!C:C, "N/A") -> SA Inc
A10: =funds_20231231!A11 -> ZARBX | B10: =funds_20231231!B11 -> 1774 | C10: {=_xlfn.XLOOKUP(1, (prices!$A:$A=A10)*(prices!$C:$C=DATE(2023,12,31)), prices!$B:$B)} -> 1.5157895 | D10: =B10*C10 -> 2689.0105 | E10: =D10/$D$49 -> 1.9379201e-05 | F10: {=(_xlfn.XLOOKUP(1, (prices!$A:$A=A10)*(prices!$C:$C=DATE(2024,12,31)), prices!$B:$B)/_xlfn.XLOOKUP(1, (prices!$A:$A=A10)*(prices!$C:$C=DATE(2023,12,31)), prices!$B:$B))-1} -> 0.8529559 | G10: =_xlfn.XLOOKUP(A10, attributes!A:A, attributes!C:C, "N/A") -> SA Inc
A11: =funds_20231231!A12 -> ZAEXX | B11: =funds_20231231!B12 -> 154023 | C11: {=_xlfn.XLOOKUP(1, (prices!$A:$A=A11)*(prices!$C:$C=DATE(2023,12,31)), prices!$B:$B)} -> 11.181408 | D11: =B11*C11 -> 1722194 | E11: =D11/$D$49 -> 0.012411534 | F11: {=(_xlfn.XLOOKUP(1, (prices!$A:$A=A11)*(prices!$C:$C=DATE(2024,12,31)), prices!$B:$B)/_xlfn.XLOOKUP(1, (prices!$A:$A=A11)*(prices!$C:$C=DATE(2023,12,31)), prices!$B:$B))-1} -> -0.25139757 | G11: =_xlfn.XLOOKUP(A11, attributes!A:A, attributes!C:C, "N/A") -> Resources
A12: =funds_20231231!A13 -> ZASPP | B12: =funds_20231231!B13 -> 293 | C12: {=_xlfn.XLOOKUP(1, (prices!$A:$A=A12)*(prices!$C:$C=DATE(2023,12,31)), prices!$B:$B)} -> 6.4470267 | D12: =B12*C12 -> 1888.9788 | E12: =D12/$D$49 -> 1.3613521e-05 | F12: {=(_xlfn.XLOOKUP(1, (prices!$A:$A=A12)*(prices!$C:$C=DATE(2024,12,31)), prices!$B:$B)/_xlfn.XLOOKUP(1, (prices!$A:$A=A12)*(prices!$C:$C=DATE(2023,12,31)), prices!$B:$B))-1} -> 0.200851 | G12: =_xlfn.XLOOKUP(A12, attributes!A:A, attributes!C:C, "N/A") -> SA Inc
A13: =funds_20231231!A14 -> ZAVKE | B13: =funds_20231231!B14 -> 1515 | C13: {=_xlfn.XLOOKUP(1, (prices!$A:$A=A13)*(prices!$C:$C=DATE(2023,12,31)), prices!$B:$B)} -> 0.7721121 | D13: =B13*C13 -> 1169.7498 | E13: =D13/$D$49 -> 8.4301706e-06 | F13: {=(_xlfn.XLOOKUP(1, (prices!$A:$A=A13)*(prices!$C:$C=DATE(2024,12,31)), prices!$B:$B)/_xlfn.XLOOKUP(1, (prices!$A:$A=A13)*(prices!$C:$C=DATE(2023,12,31)), prices!$B:$B))-1} -> 0.23337693 | G13: =_xlfn.XLOOKUP(A13, attributes!A:A, attributes!C:C, "N/A") -> Property
... A47: =funds_20231231!A48 -> ZAARI | B47: =funds_20231231!B48 -> 86807 | C47: {=_xlfn.XLOOKUP(1, (prices!$A:$A=A47)*(prices!$C:$C=DATE(2023,12,31)), prices!$B:$B)} -> 10.936432 | D47: =B47*C47 -> 949358.85 | E47: =D47/$D$49 -> 0.0068418536 | F47: {=(_xlfn.XLOOKUP(1, (prices!$A:$A=A47)*(prices!$C:$C=DATE(2024,12,31)), prices!$B:$B)/_xlfn.XLOOKUP(1, (prices!$A:$A=A47)*(prices!$C:$C=DATE(2023,12,31)), prices!$B:$B))-1} -> -0.27126202 | G47: =_xlfn.XLOOKUP(A47, attributes!A:A, attributes!C:C, "N/A") -> Resources
C49: total market value: | D49: =SUM(D2:D47) -> 1.3875755e+08

Sheet 2_monthlyReturns
A1: Asset ID | B1: 45292 | C1: 45323 | D1: 45352 | E1: 45383 | F1: 45413 | G1: 45444 | H1: 45474 | I1: 45505 | J1: 45536 | K1: 45566 | L1: 45597 | M1: 45627
A2: =funds_20231231!A3 -> ZAMNP | B2: {=(_xlfn.XLOOKUP(1, (prices!$A:$A=$A2)*(prices!$C:$C=DATEVALUE("2024-01-31")), prices!$B:$B)/_xlfn.XLOOKUP(1, (prices!$A:$A=$A2)*(prices!$C:$C=DATE(2023,12,31)), prices!$B:$B))-1} -> -0.087595085 | C2: {=(_xlfn.XLOOKUP(1, (prices!$A:$A=$A2)*(prices!$C:$C=DATEVALUE("2024-02-29")), prices!$B:$B)/_xlfn.XLOOKUP(1, (prices!$A:$A=$A2)*(prices!$C:$C=DATEVALUE("2024-01-31")), prices!$B:$B))-1} -> -0.016966844 | D2: {=(_xlfn.XLOOKUP(1, (prices!$A:$A=$A2)*(prices!$C:$C=DATEVALUE("2024-03-31")), prices!$B:$B)/_xlfn.XLOOKUP(1, (prices!$A:$A=$A2)*(prices!$C:$C=DATEVALUE("2024-02-29")), prices!$B:$B))-1} -> -0.0095321454 | E2: {=(_xlfn.XLOOKUP(1, (prices!$A:$A=$A2)*(prices!$C:$C=DATEVALUE("2024-04-30")), prices!$B:$B)/_xlfn.XLOOKUP(1, (prices!$A:$A=$A2)*(prices!$C:$C=DATEVALUE("2024-03-31")), prices!$B:$B))-1} -> 0.08250579 | F2: {=(_xlfn.XLOOKUP(1, (prices!$A:$A=$A2)*(prices!$C:$C=DATEVALUE("2024-05-31")), prices!$B:$B)/_xlfn.XLOOKUP(1, (prices!$A:$A=$A2)*(prices!$C:$C=DATEVALUE("2024-04-30")), prices!$B:$B))-1} -> 0.03359978 | G2: {=(_xlfn.XLOOKUP(1, (prices!$A:$A=$A2)*(prices!$C:$C=DATEVALUE("2024-06-30")), prices!$B:$B)/_xlfn.XLOOKUP(1, (prices!$A:$A=$A2)*(prices!$C:$C=DATEVALUE("2024-05-31")), prices!$B:$B))-1} -> -0.022963472 | H2: {=(_xlfn.XLOOKUP(1, (prices!$A:$A=$A2)*(prices!$C:$C=DATEVALUE("2024-07-31")), prices!$B:$B)/_xlfn.XLOOKUP(1, (prices!$A:$A=$A2)*(prices!$C:$C=DATEVALUE("2024-06-30")), prices!$B:$B))-1} -> 0.018978561 | I2: {=(_xlfn.XLOOKUP(1, (prices!$A:$A=$A2)*(prices!$C:$C=DATEVALUE("2024-08-31")), prices!$B:$B)/_xlfn.XLOOKUP(1, (prices!$A:$A=$A2)*(prices!$C:$C=DATEVALUE("2024-07-31")), prices!$B:$B))-1} -> -0.011213299 | J2: {=(_xlfn.XLOOKUP(1, (prices!$A:$A=$A2)*(prices!$C:$C=DATEVALUE("2024-09-30")), prices!$B:$B)/_xlfn.XLOOKUP(1, (prices!$A:$A=$A2)*(prices!$C:$C=DATEVALUE("2024-08-31")), prices!$B:$B))-1} -> -0.02351838 | K2: {=(_xlfn.XLOOKUP(1, (prices!$A:$A=$A2)*(prices!$C:$C=DATEVALUE("2024-10-31")), prices!$B:$B)/_xlfn.XLOOKUP(1, (prices!$A:$A=$A2)*(prices!$C:$C=DATEVALUE("2024-09-30")), prices!$B:$B))-1} -> -0.15354786 | L2: {=(_xlfn.XLOOKUP(1, (prices!$A:$A=$A2)*(prices!$C:$C=DATEVALUE("2024-11-30")), prices!$B:$B)/_xlfn.XLOOKUP(1, (prices!$A:$A=$A2)*(prices!$C:$C=DATEVALUE("2024-10-31")), prices!$B:$B))-1} -> -0.062728305 | M2: {=(_xlfn.XLOOKUP(1, (prices!$A:$A=$A2)*(prices!$C:$C=DATEVALUE("2024-12-31")), prices!$B:$B)/_xlfn.XLOOKUP(1, (prices!$A:$A=$A2)*(prices!$C:$C=DATEVALUE("2024-11-30")), prices!$B:$B))-1} -> -0.022651279
A3: =funds_20231231!A4 -> ZABTI | B3: {=(_xlfn.XLOOKUP(1, (prices!$A:$A=$A3)*(prices!$C:$C=DATEVALUE("2024-01-31")), prices!$B:$B)/_xlfn.XLOOKUP(1, (prices!$A:$A=$A3)*(prices!$C:$C=DATE(2023,12,31)), prices!$B:$B))-1} -> 0.012753331 | C3: {=(_xlfn.XLOOKUP(1, (prices!$A:$A=$A3)*(prices!$C:$C=DATEVALUE("2024-02-29")), prices!$B:$B)/_xlfn.XLOOKUP(1, (prices!$A:$A=$A3)*(prices!$C:$C=DATEVALUE("2024-01-31")), prices!$B:$B))-1} -> -0.0015701835 | D3: {=(_xlfn.XLOOKUP(1, (prices!$A:$A=$A3)*(prices!$C:$C=DATEVALUE("2024-03-31")), prices!$B:$B)/_xlfn.XLOOKUP(1, (prices!$A:$A=$A3)*(prices!$C:$C=DATEVALUE("2024-02-29")), prices!$B:$B))-1} -> 0.017902796 | E3: {=(_xlfn.XLOOKUP(1, (prices!$A:$A=$A3)*(prices!$C:$C=DATEVALUE("2024-04-30")), prices!$B:$B)/_xlfn.XLOOKUP(1, (prices!$A:$A=$A3)*(prices!$C:$C=DATEVALUE("2024-03-31")), prices!$B:$B))-1} -> -0.034950742 | F3: {=(_xlfn.XLOOKUP(1, (prices!$A:$A=$A3)*(prices!$C:$C=DATEVALUE("2024-05-31")), prices!$B:$B)/_xlfn.XLOOKUP(1, (prices!$A:$A=$A3)*(prices!$C:$C=DATEVALUE("2024-04-30")), prices!$B:$B))-1} -> 0.045578765 | G3: {=(_xlfn.XLOOKUP(1, (prices!$A:$A=$A3)*(prices!$C:$C=DATEVALUE("2024-06-30")), prices!$B:$B)/_xlfn.XLOOKUP(1, (prices!$A:$A=$A3)*(prices!$C:$C=DATEVALUE("2024-05-31")), prices!$B:$B))-1} -> 0.00023553469 | H3: {=(_xlfn.XLOOKUP(1, (prices!$A:$A=$A3)*(prices!$C:$C=DATEVALUE("2024-07-31")), prices!$B:$B)/_xlfn.XLOOKUP(1, (prices!$A:$A=$A3)*(prices!$C:$C=DATEVALUE("2024-06-30")), prices!$B:$B))-1} -> 0.14367361 | I3: {=(_xlfn.XLOOKUP(1, (prices!$A:$A=$A3)*(prices!$C:$C=DATEVALUE("2024-08-31")), prices!$B:$B)/_xlfn.XLOOKUP(1, (prices!$A:$A=$A3)*(prices!$C:$C=DATEVALUE("2024-07-31")), prices!$B:$B))-1} -> 0.056814513 | J3: {=(_xlfn.XLOOKUP(1, (prices!$A:$A=$A3)*(prices!$C:$C=DATEVALUE("2024-09-30")), prices!$B:$B)/_xlfn.XLOOKUP(1, (prices!$A:$A=$A3)*(prices!$C:$C=DATEVALUE("2024-08-31")), prices!$B:$B))-1} -> -0.016770391 | K3: {=(_xlfn.XLOOKUP(1, (prices!$A:$A=$A3)*(prices!$C:$C=DATEVALUE("2024-10-31")), prices!$B:$B)/_xlfn.XLOOKUP(1, (prices!$A:$A=$A3)*(prices!$C:$C=DATEVALUE("2024-09-30")), prices!$B:$B))-1} -> -0.056086827 | L3: {=(_xlfn.XLOOKUP(1, (prices!$A:$A=$A3)*(prices!$C:$C=DATEVALUE("2024-11-30")), prices!$B:$B)/_xlfn.XLOOKUP(1, (prices!$A:$A=$A3)*(prices!$C:$C=DATEVALUE("2024-10-31")), prices!$B:$B))-1} -> 0.095974172 | M3: {=(_xlfn.XLOOKUP(1, (prices!$A:$A=$A3)*(prices!$C:$C=DATEVALUE("2024-12-31")), prices!$B:$B)/_xlfn.XLOOKUP(1, (prices!$A:$A=$A3)*(prices!$C:$C=DATEVALUE("2024-11-30")), prices!$B:$B))-1} -> -0.051877473
A4: =funds_20231231!A5 -> ZAINP | B4: {=(_xlfn.XLOOKUP(1, (prices!$A:$A=$A4)*(prices!$C:$C=DATEVALUE("2024-01-31")), prices!$B:$B)/_xlfn.XLOOKUP(1, (prices!$A:$A=$A4)*(prices!$C:$C=DATE(2023,12,31)), prices!$B:$B))-1} -> -0.032895048 | C4: {=(_xlfn.XLOOKUP(1, (prices!$A:$A=$A4)*(prices!$C:$C=DATEVALUE("2024-02-29")), prices!$B:$B)/_xlfn.XLOOKUP(1, (prices!$A:$A=$A4)*(prices!$C:$C=DATEVALUE("2024-01-31")), prices!$B:$B))-1} -> -0.063207933 | D4: {=(_xlfn.XLOOKUP(1, (prices!$A:$A=$A4)*(prices!$C:$C=DATEVALUE("2024-03-31")), prices!$B:$B)/_xlfn.XLOOKUP(1, (prices!$A:$A=$A4)*(prices!$C:$C=DATEVALUE("2024-02-29")), prices!$B:$B))-1} -> 0.068759407 | E4: {=(_xlfn.XLOOKUP(1, (prices!$A:$A=$A4)*(prices!$C:$C=DATEVALUE("2024-04-30")), prices!$B:$B)/_xlfn.XLOOKUP(1, (prices!$A:$A=$A4)*(prices!$C:$C=DATEVALUE("2024-03-31")), prices!$B:$B))-1} -> -0.039002975 | F4: {=(_xlfn.XLOOKUP(1, (prices!$A:$A=$A4)*(prices!$C:$C=DATEVALUE("2024-05-31")), prices!$B:$B)/_xlfn.XLOOKUP(1, (prices!$A:$A=$A4)*(prices!$C:$C=DATEVALUE("2024-04-30")), prices!$B:$B))-1} -> 0.020323847 | G4: {=(_xlfn.XLOOKUP(1, (prices!$A:$A=$A4)*(prices!$C:$C=DATEVALUE("2024-06-30")), prices!$B:$B)/_xlfn.XLOOKUP(1, (prices!$A:$A=$A4)*(prices!$C:$C=DATEVALUE("2024-05-31")), prices!$B:$B))-1} -> 0.10804755 | H4: {=(_xlfn.XLOOKUP(1, (prices!$A:$A=$A4)*(prices!$C:$C=DATEVALUE("2024-07-31")), prices!$B:$B)/_xlfn.XLOOKUP(1, (prices!$A:$A=$A4)*(prices!$C:$C=DATEVALUE("2024-06-30")), prices!$B:$B))-1} -> 0.087162014 | I4: {=(_xlfn.XLOOKUP(1, (prices!$A:$A=$A4)*(prices!$C:$C=DATEVALUE("2024-08-31")), prices!$B:$B)/_xlfn.XLOOKUP(1, (prices!$A:$A=$A4)*(prices!$C:$C=DATEVALUE("2024-07-31")), prices!$B:$B))-1} -> -0.031202017 | J4: {=(_xlfn.XLOOKUP(1, (prices!$A:$A=$A4)*(prices!$C:$C=DATEVALUE("2024-09-30")), prices!$B:$B)/_xlfn.XLOOKUP(1, (prices!$A:$A=$A4)*(prices!$C:$C=DATEVALUE("2024-08-31")), prices!$B:$B))-1} -> -0.0038231561 | K4: {=(_xlfn.XLOOKUP(1, (prices!$A:$A=$A4)*(prices!$C:$C=DATEVALUE("2024-10-31")), prices!$B:$B)/_xlfn.XLOOKUP(1, (prices!$A:$A=$A4)*(prices!$C:$C=DATEVALUE("2024-09-30")), prices!$B:$B))-1} -> 0.019926384 | L4: {=(_xlfn.XLOOKUP(1, (prices!$A:$A=$A4)*(prices!$C:$C=DATEVALUE("2024-11-30")), prices!$B:$B)/_xlfn.XLOOKUP(1, (prices!$A:$A=$A4)*(prices!$C:$C=DATEVALUE("2024-10-31")), prices!$B:$B))-1} -> -0.072866647 | M4: {=(_xlfn.XLOOKUP(1, (prices!$A:$A=$A4)*(prices!$C:$C=DATEVALUE("2024-12-31")), prices!$B:$B)/_xlfn.XLOOKUP(1, (prices!$A:$A=$A4)*(prices!$C:$C=DATEVALUE("2024-11-30")), prices!$B:$B))-1} -> -0.065948817
A5: =funds_20231231!A6 -> ZACFR | B5: {=(_xlfn.XLOOKUP(1, (prices!$A:$A=$A5)*(prices!$C:$C=DATEVALUE("2024-01-31")), prices!$B:$B)/_xlfn.XLOOKUP(1, (prices!$A:$A=$A5)*(prices!$C:$C=DATE(2023,12,31)), prices!$B:$B))-1} -> 0.078309245 | C5: {=(_xlfn.XLOOKUP(1, (prices!$A:$A=$A5)*(prices!$C:$C=DATEVALUE("2024-02-29")), prices!$B:$B)/_xlfn.XLOOKUP(1, (prices!$A:$A=$A5)*(prices!$C:$C=DATEVALUE("2024-01-31")), prices!$B:$B))-1} -> 0.05616803 | D5: {=(_xlfn.XLOOKUP(1, (prices!$A:$A=$A5)*(prices!$C:$C=DATEVALUE("2024-03-31")), prices!$B:$B)/_xlfn.XLOOKUP(1, (prices!$A:$A=$A5)*(prices!$C:$C=DATEVALUE("2024-02-29")), prices!$B:$B))-1} -> -0.046393004 | E5: {=(_xlfn.XLOOKUP(1, (prices!$A:$A=$A5)*(prices!$C:$C=DATEVALUE("2024-04-30")), prices!$B:$B)/_xlfn.XLOOKUP(1, (prices!$A:$A=$A5)*(prices!$C:$C=DATEVALUE("2024-03-31")), prices!$B:$B))-1} -> -0.078075082 | F5: {=(_xlfn.XLOOKUP(1, (prices!$A:$A=$A5)*(prices!$C:$C=DATEVALUE("2024-05-31")), prices!$B:$B)/_xlfn.XLOOKUP(1, (prices!$A:$A=$A5)*(prices!$C:$C=DATEVALUE("2024-04-30")), prices!$B:$B))-1} -> 0.12724246 | G5: {=(_xlfn.XLOOKUP(1, (prices!$A:$A=$A5)*(prices!$C:$C=DATEVALUE("2024-06-30")), prices!$B:$B)/_xlfn.XLOOKUP(1, (prices!$A:$A=$A5)*(prices!$C:$C=DATEVALUE("2024-05-31")), prices!$B:$B))-1} -> -0.015085548 | H5: {=(_xlfn.XLOOKUP(1, (prices!$A:$A=$A5)*(prices!$C:$C=DATEVALUE("2024-07-31")), prices!$B:$B)/_xlfn.XLOOKUP(1, (prices!$A:$A=$A5)*(prices!$C:$C=DATEVALUE("2024-06-30")), prices!$B:$B))-1} -> -0.02498948 | I5: {=(_xlfn.XLOOKUP(1, (prices!$A:$A=$A5)*(prices!$C:$C=DATEVALUE("2024-08-31")), prices!$B:$B)/_xlfn.XLOOKUP(1, (prices!$A:$A=$A5)*(prices!$C:$C=DATEVALUE("2024-07-31")), prices!$B:$B))-1} -> 0.035448259 | J5: {=(_xlfn.XLOOKUP(1, (prices!$A:$A=$A5)*(prices!$C:$C=DATEVALUE("2024-09-30")), prices!$B:$B)/_xlfn.XLOOKUP(1, (prices!$A:$A=$A5)*(prices!$C:$C=DATEVALUE("2024-08-31")), prices!$B:$B))-1} -> 0.0072292476 | K5: {=(_xlfn.XLOOKUP(1, (prices!$A:$A=$A5)*(prices!$C:$C=DATEVALUE("2024-10-31")), prices!$B:$B)/_xlfn.XLOOKUP(1, (prices!$A:$A=$A5)*(prices!$C:$C=DATEVALUE("2024-09-30")), prices!$B:$B))-1} -> -0.093120522 | L5: {=(_xlfn.XLOOKUP(1, (prices!$A:$A=$A5)*(prices!$C:$C=DATEVALUE("2024-11-30")), prices!$B:$B)/_xlfn.XLOOKUP(1, (prices!$A:$A=$A5)*(prices!$C:$C=DATEVALUE("2024-10-31")), prices!$B:$B))-1} -> -0.042279688 | M5: {=(_xlfn.XLOOKUP(1, (prices!$A:$A=$A5)*(prices!$C:$C=DATEVALUE("2024-12-31")), prices!$B:$B)/_xlfn.XLOOKUP(1, (prices!$A:$A=$A5)*(prices!$C:$C=DATEVALUE("2024-11-30")), prices!$B:$B))-1} -> 0.067199753
A6: =funds_20231231!A7 -> ZAATT | B6: {=(_xlfn.XLOOKUP(1, (prices!$A:$A=$A6)*(prices!$C:$C=DATEVALUE("2024-01-31")), prices!$B:$B)/_xlfn.XLOOKUP(1, (prices!$A:$A=$A6)*(prices!$C:$C=DATE(2023,12,31)), prices!$B:$B))-1} -> 0.062182152 | C6: {=(_xlfn.XLOOKUP(1, (prices!$A:$A=$A6)*(prices!$C:$C=DATEVALUE("2024-02-29")), prices!$B:$B)/_xlfn.XLOOKUP(1, (prices!$A:$A=$A6)*(prices!$C:$C=DATEVALUE("2024-01-31")), prices!$B:$B))-1} -> -0.065536925 | D6: {=(_xlfn.XLOOKUP(1, (prices!$A:$A=$A6)*(prices!$C:$C=DATEVALUE("2024-03-31")), prices!$B:$B)/_xlfn.XLOOKUP(1, (prices!$A:$A=$A6)*(prices!$C:$C=DATEVALUE("2024-02-29")), prices!$B:$B))-1} -> 0.12598528 | E6: {=(_xlfn.XLOOKUP(1, (prices!$A:$A=$A6)*(prices!$C:$C=DATEVALUE("2024-04-30")), prices!$B:$B)/_xlfn.XLOOKUP(1, (prices!$A:$A=$A6)*(prices!$C:$C=DATEVALUE("2024-03-31")), prices!$B:$B))-1} -> -0.048365187 | F6: {=(_xlfn.XLOOKUP(1, (prices!$A:$A=$A6)*(prices!$C:$C=DATEVALUE("2024-05-31")), prices!$B:$B)/_xlfn.XLOOKUP(1, (prices!$A:$A=$A6)*(prices!$C:$C=DATEVALUE("2024-04-30")), prices!$B:$B))-1} -> -0.011453454 | G6: {=(_xlfn.XLOOKUP(1, (prices!$A:$A=$A6)*(prices!$C:$C=DATEVALUE("2024-06-30")), prices!$B:$B)/_xlfn.XLOOKUP(1, (prices!$A:$A=$A6)*(prices!$C:$C=DATEVALUE("2024-05-31")), prices!$B:$B))-1} -> 0.12096249 | H6: {=(_xlfn.XLOOKUP(1, (prices!$A:$A=$A6)*(prices!$C:$C=DATEVALUE("2024-07-31")), prices!$B:$B)/_xlfn.XLOOKUP(1, (prices!$A:$A=$A6)*(prices!$C:$C=DATEVALUE("2024-06-30")), prices!$B:$B))-1} -> 0.011180427 | I6: {=(_xlfn.XLOOKUP(1, (prices!$A:$A=$A6)*(prices!$C:$C=DATEVALUE("2024-08-31")), prices!$B:$B)/_xlfn.XLOOKUP(1, (prices!$A:$A=$A6)*(prices!$C:$C=DATEVALUE("2024-07-31")), prices!$B:$B))-1} -> 0.07987673 | J6: {=(_xlfn.XLOOKUP(1, (prices!$A:$A=$A6)*(prices!$C:$C=DATEVALUE("2024-09-30")), prices!$B:$B)/_xlfn.XLOOKUP(1, (prices!$A:$A=$A6)*(prices!$C:$C=DATEVALUE("2024-08-31")), prices!$B:$B))-1} -> 0.16179382 | K6: {=(_xlfn.XLOOKUP(1, (prices!$A:$A=$A6)*(prices!$C:$C=DATEVALUE("2024-10-31")), prices!$B:$B)/_xlfn.XLOOKUP(1, (prices!$A:$A=$A6)*(prices!$C:$C=DATEVALUE("2024-09-30")), prices!$B:$B))-1} -> -0.015556693 | L6: {=(_xlfn.XLOOKUP(1, (prices!$A:$A=$A6)*(prices!$C:$C=DATEVALUE("2024-11-30")), prices!$B:$B)/_xlfn.XLOOKUP(1, (prices!$A:$A=$A6)*(prices!$C:$C=DATEVALUE("2024-10-31")), prices!$B:$B))-1} -> -0.01751419 | M6: {=(_xlfn.XLOOKUP(1, (prices!$A:$A=$A6)*(prices!$C:$C=DATEVALUE("2024-12-31")), prices!$B:$B)/_xlfn.XLOOKUP(1, (prices!$A:$A=$A6)*(prices!$C:$C=DATEVALUE("2024-11-30")), prices!$B:$B))-1} -> 0.0081535877
A7: =funds_20231231!A8 -> ZAAGL | B7: {=(_xlfn.XLOOKUP(1, (prices!$A:$A=$A7)*(prices!$C:$C=DATEVALUE("2024-01-31")), prices!$B:$B)/_xlfn.XLOOKUP(1, (prices!$A:$A=$A7)*(prices!$C:$C=DATE(2023,12,31)), prices!$B:$B))-1} -> -0.061112645 | C7: {=(_xlfn.XLOOKUP(1, (prices!$A:$A=$A7)*(prices!$C:$C=DATEVALUE("2024-02-29")), prices!$B:$B)/_xlfn.XLOOKUP(1, (prices!$A:$A=$A7)*(prices!$C:$C=DATEVALUE("2024-01-31")), prices!$B:$B))-1} -> -0.09896379 | D7: {=(_xlfn.XLOOKUP(1, (prices!$A:$A=$A7)*(prices!$C:$C=DATEVALUE("2024-03-31")), prices!$B:$B)/_xlfn.XLOOKUP(1, (prices!$A:$A=$A7)*(prices!$C:$C=DATEVALUE("2024-02-29")), prices!$B:$B))-1} -> 0.12149199 | E7: {=(_xlfn.XLOOKUP(1, (prices!$A:$A=$A7)*(prices!$C:$C=DATEVALUE("2024-04-30")), prices!$B:$B)/_xlfn.XLOOKUP(1, (prices!$A:$A=$A7)*(prices!$C:$C=DATEVALUE("2024-03-31")), prices!$B:$B))-1} -> 0.33350967 | F7: {=(_xlfn.XLOOKUP(1, (prices!$A:$A=$A7)*(prices!$C:$C=DATEVALUE("2024-05-31")), prices!$B:$B)/_xlfn.XLOOKUP(1, (prices!$A:$A=$A7)*(prices!$C:$C=DATEVALUE("2024-04-30")), prices!$B:$B))-1} -> -0.037411699 | G7: {=(_xlfn.XLOOKUP(1, (prices!$A:$A=$A7)*(prices!$C:$C=DATEVALUE("2024-06-30")), prices!$B:$B)/_xlfn.XLOOKUP(1, (prices!$A:$A=$A7)*(prices!$C:$C=DATEVALUE("2024-05-31")), prices!$B:$B))-1} -> 0.0012750788 | H7: {=(_xlfn.XLOOKUP(1, (prices!$A:$A=$A7)*(prices!$C:$C=DATEVALUE("2024-07-31")), prices!$B:$B)/_xlfn.XLOOKUP(1, (prices!$A:$A=$A7)*(prices!$C:$C=DATEVALUE("2024-06-30")), prices!$B:$B))-1} -> -0.039418914 | I7: {=(_xlfn.XLOOKUP(1, (prices!$A:$A=$A7)*(prices!$C:$C=DATEVALUE("2024-08-31")), prices!$B:$B)/_xlfn.XLOOKUP(1, (prices!$A:$A=$A7)*(prices!$C:$C=DATEVALUE("2024-07-31")), prices!$B:$B))-1} -> -0.042361107 | J7: {=(_xlfn.XLOOKUP(1, (prices!$A:$A=$A7)*(prices!$C:$C=DATEVALUE("2024-09-30")), prices!$B:$B)/_xlfn.XLOOKUP(1, (prices!$A:$A=$A7)*(prices!$C:$C=DATEVALUE("2024-08-31")), prices!$B:$B))-1} -> 0.11725798 | K7: {=(_xlfn.XLOOKUP(1, (prices!$A:$A=$A7)*(prices!$C:$C=DATEVALUE("2024-10-31")), prices!$B:$B)/_xlfn.XLOOKUP(1, (prices!$A:$A=$A7)*(prices!$C:$C=DATEVALUE("2024-09-30")), prices!$B:$B))-1} -> -0.05285255 | L7: {=(_xlfn.XLOOKUP(1, (prices!$A:$A=$A7)*(prices!$C:$C=DATEVALUE("2024-11-30")), prices!$B:$B)/_xlfn.XLOOKUP(1, (prices!$A:$A=$A7)*(prices!$C:$C=DATEVALUE("2024-10-31")), prices!$B:$B))-1} -> 0.023770348 | M7: {=(_xlfn.XLOOKUP(1, (prices!$A:$A=$A7)*(prices!$C:$C=DATEVALUE("2024-12-31")), prices!$B:$B)/_xlfn.XLOOKUP(1, (prices!$A:$A=$A7)*(prices!$C:$C=DATEVALUE("2024-11-30")), prices!$B:$B))-1} -> -0.070517545
A8: =funds_20231231!A9 -> ZALHC | B8: {=(_xlfn.XLOOKUP(1, (prices!$A:$A=$A8)*(prices!$C:$C=DATEVALUE("2024-01-31")), prices!$B:$B)/_xlfn.XLOOKUP(1, (prices!$A:$A=$A8)*(prices!$C:$C=DATE(2023,12,31)), prices!$B:$B))-1} -> -0.010311925 | C8: {=(_xlfn.XLOOKUP(1, (prices!$A:$A=$A8)*(prices!$C:$C=DATEVALUE("2024-02-29")), prices!$B:$B)/_xlfn.XLOOKUP(1, (prices!$A:$A=$A8)*(prices!$C:$C=DATEVALUE("2024-01-31")), prices!$B:$B))-1} -> -0.079782559 | D8: {=(_xlfn.XLOOKUP(1, (prices!$A:$A=$A8)*(prices!$C:$C=DATEVALUE("2024-03-31")), prices!$B:$B)/_xlfn.XLOOKUP(1, (prices!$A:$A=$A8)*(prices!$C:$C=DATEVALUE("2024-02-29")), prices!$B:$B))-1} -> -0.0077107569 | E8: {=(_xlfn.XLOOKUP(1, (prices!$A:$A=$A8)*(prices!$C:$C=DATEVALUE("2024-04-30")), prices!$B:$B)/_xlfn.XLOOKUP(1, (prices!$A:$A=$A8)*(prices!$C:$C=DATEVALUE("2024-03-31")), prices!$B:$B))-1} -> -0.37071155 | F8: {=(_xlfn.XLOOKUP(1, (prices!$A:$A=$A8)*(prices!$C:$C=DATEVALUE("2024-05-31")), prices!$B:$B)/_xlfn.XLOOKUP(1, (prices!$A:$A=$A8)*(prices!$C:$C=DATEVALUE("2024-04-30")), prices!$B:$B))-1} -> 0.029255758 | G8: {=(_xlfn.XLOOKUP(1, (prices!$A:$A=$A8)*(prices!$C:$C=DATEVALUE("2024-06-30")), prices!$B:$B)/_xlfn.XLOOKUP(1, (prices!$A:$A=$A8)*(prices!$C:$C=DATEVALUE("2024-05-31")), prices!$B:$B))-1} -> 0.19687113 | H8: {=(_xlfn.XLOOKUP(1, (prices!$A:$A=$A8)*(prices!$C:$C=DATEVALUE("2024-07-31")), prices!$B:$B)/_xlfn.XLOOKUP(1, (prices!$A:$A=$A8)*(prices!$C:$C=DATEVALUE("2024-06-30")), prices!$B:$B))-1} -> 0.042836849 | I8: {=(_xlfn.XLOOKUP(1, (prices!$A:$A=$A8)*(prices!$C:$C=DATEVALUE("2024-08-31")), prices!$B:$B)/_xlfn.XLOOKUP(1, (prices!$A:$A=$A8)*(prices!$C:$C=DATEVALUE("2024-07-31")), prices!$B:$B))-1} -> 0.10285234 | J8: {=(_xlfn.XLOOKUP(1, (prices!$A:$A=$A8)*(prices!$C:$C=DATEVALUE("2024-09-30")), prices!$B:$B)/_xlfn.XLOOKUP(1, (prices!$A:$A=$A8)*(prices!$C:$C=DATEVALUE("2024-08-31")), prices!$B:$B))-1} -> 0.14719066 | K8: {=(_xlfn.XLOOKUP(1, (prices!$A:$A=$A8)*(prices!$C:$C=DATEVALUE("2024-10-31")), prices!$B:$B)/_xlfn.XLOOKUP(1, (prices!$A:$A=$A8)*(prices!$C:$C=DATEVALUE("2024-09-30")), prices!$B:$B))-1} -> -0.028356989 | L8: {=(_xlfn.XLOOKUP(1, (prices!$A:$A=$A8)*(prices!$C:$C=DATEVALUE("2024-11-30")), prices!$B:$B)/_xlfn.XLOOKUP(1, (prices!$A:$A=$A8)*(prices!$C:$C=DATEVALUE("2024-10-31")), prices!$B:$B))-1} -> 0.023551515 | M8: {=(_xlfn.XLOOKUP(1, (prices!$A:$A=$A8)*(prices!$C:$C=DATEVALUE("2024-12-31")), prices!$B:$B)/_xlfn.XLOOKUP(1, (prices!$A:$A=$A8)*(prices!$C:$C=DATEVALUE("2024-11-30")), prices!$B:$B))-1} -> -0.059943698
A9: =funds_20231231!A10 -> ZAVOD | B9: {=(_xlfn.XLOOKUP(1, (prices!$A:$A=$A9)*(prices!$C:$C=DATEVALUE("2024-01-31")), prices!$B:$B)/_xlfn.XLOOKUP(1, (prices!$A:$A=$A9)*(prices!$C:$C=DATE(2023,12,31)), prices!$B:$B))-1} -> -0.13398471 | C9: {=(_xlfn.XLOOKUP(1, (prices!$A:$A=$A9)*(prices!$C:$C=DATEVALUE("2024-02-29")), prices!$B:$B)/_xlfn.XLOOKUP(1, (prices!$A:$A=$A9)*(prices!$C:$C=DATEVALUE("2024-01-31")), prices!$B:$B))-1} -> -0.023640729 | D9: {=(_xlfn.XLOOKUP(1, (prices!$A:$A=$A9)*(prices!$C:$C=DATEVALUE("2024-03-31")), prices!$B:$B)/_xlfn.XLOOKUP(1, (prices!$A:$A=$A9)*(prices!$C:$C=DATEVALUE("2024-02-29")), prices!$B:$B))-1} -> 0.061881145 | E9: {=(_xlfn.XLOOKUP(1, (prices!$A:$A=$A9)*(prices!$C:$C=DATEVALUE("2024-04-30")), prices!$B:$B)/_xlfn.XLOOKUP(1, (prices!$A:$A=$A9)*(prices!$C:$C=DATEVALUE("2024-03-31")), prices!$B:$B))-1} -> -0.077289826 | F9: {=(_xlfn.XLOOKUP(1, (prices!$A:$A=$A9)*(prices!$C:$C=DATEVALUE("2024-05-31")), prices!$B:$B)/_xlfn.XLOOKUP(1, (prices!$A:$A=$A9)*(prices!$C:$C=DATEVALUE("2024-04-30")), prices!$B:$B))-1} -> 0.022554113 | G9: {=(_xlfn.XLOOKUP(1, (prices!$A:$A=$A9)*(prices!$C:$C=DATEVALUE("2024-06-30")), prices!$B:$B)/_xlfn.XLOOKUP(1, (prices!$A:$A=$A9)*(prices!$C:$C=DATEVALUE("2024-05-31")), prices!$B:$B))-1} -> 0.087512166 | H9: {=(_xlfn.XLOOKUP(1, (prices!$A:$A=$A9)*(prices!$C:$C=DATEVALUE("2024-07-31")), prices!$B:$B)/_xlfn.XLOOKUP(1, (prices!$A:$A=$A9)*(prices!$C:$C=DATEVALUE("2024-06-30")), prices!$B:$B))-1} -> 0.052264578 | I9: {=(_xlfn.XLOOKUP(1, (prices!$A:$A=$A9)*(prices!$C:$C=DATEVALUE("2024-08-31")), prices!$B:$B)/_xlfn.XLOOKUP(1, (prices!$A:$A=$A9)*(prices!$C:$C=DATEVALUE("2024-07-31")), prices!$B:$B))-1} -> 0.10295189 | J9: {=(_xlfn.XLOOKUP(1, (prices!$A:$A=$A9)*(prices!$C:$C=DATEVALUE("2024-09-30")), prices!$B:$B)/_xlfn.XLOOKUP(1, (prices!$A:$A=$A9)*(prices!$C:$C=DATEVALUE("2024-08-31")), prices!$B:$B))-1} -> 0.024983622 | K9: {=(_xlfn.XLOOKUP(1, (prices!$A:$A=$A9)*(prices!$C:$C=DATEVALUE("2024-10-31")), prices!$B:$B)/_xlfn.XLOOKUP(1, (prices!$A:$A=$A9)*(prices!$C:$C=DATEVALUE("2024-09-30")), prices!$B:$B))-1} -> -0.020592121 | L9: {=(_xlfn.XLOOKUP(1, (prices!$A:$A=$A9)*(prices!$C:$C=DATEVALUE("2024-11-30")), prices!$B:$B)/_xlfn.XLOOKUP(1, (prices!$A:$A=$A9)*(prices!$C:$C=DATEVALUE("2024-10-31")), prices!$B:$B))-1} -> -0.098476935 | M9: {=(_xlfn.XLOOKUP(1, (prices!$A:$A=$A9)*(prices!$C:$C=DATEVALUE("2024-12-31")), prices!$B:$B)/_xlfn.XLOOKUP(1, (prices!$A:$A=$A9)*(prices!$C:$C=DATEVALUE("2024-11-30")), prices!$B:$B))-1} -> -0.042348629
A10: =funds_20231231!A11 -> ZARBX | B10: {=(_xlfn.XLOOKUP(1, (prices!$A:$A=$A10)*(prices!$C:$C=DATEVALUE("2024-01-31")), prices!$B:$B)/_xlfn.XLOOKUP(1, (prices!$A:$A=$A10)*(prices!$C:$C=DATE(2023,12,31)), prices!$B:$B))-1} -> 0.064139615 | C10: {=(_xlfn.XLOOKUP(1, (prices!$A:$A=$A10)*(prices!$C:$C=DATEVALUE("2024-02-29")), prices!$B:$B)/_xlfn.XLOOKUP(1, (prices!$A:$A=$A10)*(prices!$C:$C=DATEVALUE("2024-01-31")), prices!$B:$B))-1} -> -0.095128255 | D10: {=(_xlfn.XLOOKUP(1, (prices!$A:$A=$A10)*(prices!$C:$C=DATEVALUE("2024-03-31")), prices!$B:$B)/_xlfn.XLOOKUP(1, (prices!$A:$A=$A10)*(prices!$C:$C=DATEVALUE("2024-02-29")), prices!$B:$B))-1} -> 0.11835711 | E10: {=(_xlfn.XLOOKUP(1, (prices!$A:$A=$A10)*(prices!$C:$C=DATEVALUE("2024-04-30")), prices!$B:$B)/_xlfn.XLOOKUP(1, (prices!$A:$A=$A10)*(prices!$C:$C=DATEVALUE("2024-03-31")), prices!$B:$B))-1} -> -0.0079942237 | F10: {=(_xlfn.XLOOKUP(1, (prices!$A:$A=$A10)*(prices!$C:$C=DATEVALUE("2024-05-31")), prices!$B:$B)/_xlfn.XLOOKUP(1, (prices!$A:$A=$A10)*(prices!$C:$C=DATEVALUE("2024-04-30")), prices!$B:$B))-1} -> 0.17296655 | G10: {=(_xlfn.XLOOKUP(1, (prices!$A:$A=$A10)*(prices!$C:$C=DATEVALUE("2024-06-30")), prices!$B:$B)/_xlfn.XLOOKUP(1, (prices!$A:$A=$A10)*(prices!$C:$C=DATEVALUE("2024-05-31")), prices!$B:$B))-1} -> 0.15333206 | H10: {=(_xlfn.XLOOKUP(1, (prices!$A:$A=$A10)*(prices!$C:$C=DATEVALUE("2024-07-31")), prices!$B:$B)/_xlfn.XLOOKUP(1, (prices!$A:$A=$A10)*(prices!$C:$C=DATEVALUE("2024-06-30")), prices!$B:$B))-1} -> 0.15183673 | I10: {=(_xlfn.XLOOKUP(1, (prices!$A:$A=$A10)*(prices!$C:$C=DATEVALUE("2024-08-31")), prices!$B:$B)/_xlfn.XLOOKUP(1, (prices!$A:$A=$A10)*(prices!$C:$C=DATEVALUE("2024-07-31")), prices!$B:$B))-1} -> 0.099348568 | J10: {=(_xlfn.XLOOKUP(1, (prices!$A:$A=$A10)*(prices!$C:$C=DATEVALUE("2024-09-30")), prices!$B:$B)/_xlfn.XLOOKUP(1, (prices!$A:$A=$A10)*(prices!$C:$C=DATEVALUE("2024-08-31")), prices!$B:$B))-1} -> 0.099148124 | K10: {=(_xlfn.XLOOKUP(1, (prices!$A:$A=$A10)*(prices!$C:$C=DATEVALUE("2024-10-31")), prices!$B:$B)/_xlfn.XLOOKUP(1, (prices!$A:$A=$A10)*(prices!$C:$C=DATEVALUE("2024-09-30")), prices!$B:$B))-1} -> -0.12010858 | L10: {=(_xlfn.XLOOKUP(1, (prices!$A:$A=$A10)*(prices!$C:$C=DATEVALUE("2024-11-30")), prices!$B:$B)/_xlfn.XLOOKUP(1, (prices!$A:$A=$A10)*(prices!$C:$C=DATEVALUE("2024-10-31")), prices!$B:$B))-1} -> 0.085649218 | M10: {=(_xlfn.XLOOKUP(1, (prices!$A:$A=$A10)*(prices!$C:$C=DATEVALUE("2024-12-31")), prices!$B:$B)/_xlfn.XLOOKUP(1, (prices!$A:$A=$A10)*(prices!$C:$C=DATEVALUE("2024-11-30")), prices!$B:$B))-1} -> -0.035630244
A11: =funds_20231231!A12 -> ZAEXX | B11: {=(_xlfn.XLOOKUP(1, (prices!$A:$A=$A11)*(prices!$C:$C=DATEVALUE("2024-01-31")), prices!$B:$B)/_xlfn.XLOOKUP(1, (prices!$A:$A=$A11)*(prices!$C:$C=DATE(2023,12,31)), prices!$B:$B))-1} -> -0.09949121 | C11: {=(_xlfn.XLOOKUP(1, (prices!$A:$A=$A11)*(prices!$C:$C=DATEVALUE("2024-02-29")), prices!$B:$B)/_xlfn.XLOOKUP(1, (prices!$A:$A=$A11)*(prices!$C:$C=DATEVALUE("2024-01-31")), prices!$B:$B))-1} -> -0.07993535 | D11: {=(_xlfn.XLOOKUP(1, (prices!$A:$A=$A11)*(prices!$C:$C=DATEVALUE("2024-03-31")), prices!$B:$B)/_xlfn.XLOOKUP(1, (prices!$A:$A=$A11)*(prices!$C:$C=DATEVALUE("2024-02-29")), prices!$B:$B))-1} -> -0.036751084 | E11: {=(_xlfn.XLOOKUP(1, (prices!$A:$A=$A11)*(prices!$C:$C=DATEVALUE("2024-04-30")), prices!$B:$B)/_xlfn.XLOOKUP(1, (prices!$A:$A=$A11)*(prices!$C:$C=DATEVALUE("2024-03-31")), prices!$B:$B))-1} -> 0.076913024 | F11: {=(_xlfn.XLOOKUP(1, (prices!$A:$A=$A11)*(prices!$C:$C=DATEVALUE("2024-05-31")), prices!$B:$B)/_xlfn.XLOOKUP(1, (prices!$A:$A=$A11)*(prices!$C:$C=DATEVALUE("2024-04-30")), prices!$B:$B))-1} -> 0.0027541956 | G11: {=(_xlfn.XLOOKUP(1, (prices!$A:$A=$A11)*(prices!$C:$C=DATEVALUE("2024-06-30")), prices!$B:$B)/_xlfn.XLOOKUP(1, (prices!$A:$A=$A11)*(prices!$C:$C=DATEVALUE("2024-05-31")), prices!$B:$B))-1} -> 0.011585941 | H11: {=(_xlfn.XLOOKUP(1, (prices!$A:$A=$A11)*(prices!$C:$C=DATEVALUE("2024-07-31")), prices!$B:$B)/_xlfn.XLOOKUP(1, (prices!$A:$A=$A11)*(prices!$C:$C=DATEVALUE("2024-06-30")), prices!$B:$B))-1} -> 0.098912754 | I11: {=(_xlfn.XLOOKUP(1, (prices!$A:$A=$A11)*(prices!$C:$C=DATEVALUE("2024-08-31")), prices!$B:$B)/_xlfn.XLOOKUP(1, (prices!$A:$A=$A11)*(prices!$C:$C=DATEVALUE("2024-07-31")), prices!$B:$B))-1} -> -0.15876591 | J11: {=(_xlfn.XLOOKUP(1, (prices!$A:$A=$A11)*(prices!$C:$C=DATEVALUE("2024-09-30")), prices!$B:$B)/_xlfn.XLOOKUP(1, (prices!$A:$A=$A11)*(prices!$C:$C=DATEVALUE("2024-08-31")), prices!$B:$B))-1} -> 0.10798103 | K11: {=(_xlfn.XLOOKUP(1, (prices!$A:$A=$A11)*(prices!$C:$C=DATEVALUE("2024-10-31")), prices!$B:$B)/_xlfn.XLOOKUP(1, (prices!$A:$A=$A11)*(prices!$C:$C=DATEVALUE("2024-09-30")), prices!$B:$B))-1} -> -0.061622582 | L11: {=(_xlfn.XLOOKUP(1, (prices!$A:$A=$A11)*(prices!$C:$C=DATEVALUE("2024-11-30")), prices!$B:$B)/_xlfn.XLOOKUP(1, (prices!$A:$A=$A11)*(prices!$C:$C=DATEVALUE("2024-10-31")), prices!$B:$B))-1} -> -0.013740312 | M11: {=(_xlfn.XLOOKUP(1, (prices!$A:$A=$A11)*(prices!$C:$C=DATEVALUE("2024-12-31")), prices!$B:$B)/_xlfn.XLOOKUP(1, (prices!$A:$A=$A11)*(prices!$C:$C=DATEVALUE("2024-11-30")), prices!$B:$B))-1} -> -0.094168815
A12: =funds_20231231!A13 -> ZASPP | B12: {=(_xlfn.XLOOKUP(1, (prices!$A:$A=$A12)*(prices!$C:$C=DATEVALUE("2024-01-31")), prices!$B:$B)/_xlfn.XLOOKUP(1, (prices!$A:$A=$A12)*(prices!$C:$C=DATE(2023,12,31)), prices!$B:$B))-1} -> -0.063854989 | C12: {=(_xlfn.XLOOKUP(1, (prices!$A:$A=$A12)*(prices!$C:$C=DATEVALUE("2024-02-29")), prices!$B:$B)/_xlfn.XLOOKUP(1, (prices!$A:$A=$A12)*(prices!$C:$C=DATEVALUE("2024-01-31")), prices!$B:$B))-1} -> -0.15659504 | D12: {=(_xlfn.XLOOKUP(1, (prices!$A:$A=$A12)*(prices!$C:$C=DATEVALUE("2024-03-31")), prices!$B:$B)/_xlfn.XLOOKUP(1, (prices!$A:$A=$A12)*(prices!$C:$C=DATEVALUE("2024-02-29")), prices!$B:$B))-1} -> -0.082478998 | E12: {=(_xlfn.XLOOKUP(1, (prices!$A:$A=$A12)*(prices!$C:$C=DATEVALUE("2024-04-30")), prices!$B:$B)/_xlfn.XLOOKUP(1, (prices!$A:$A=$A12)*(prices!$C:$C=DATEVALUE("2024-03-31")), prices!$B:$B))-1} -> 0.099918464 | F12: {=(_xlfn.XLOOKUP(1, (prices!$A:$A=$A12)*(prices!$C:$C=DATEVALUE("2024-05-31")), prices!$B:$B)/_xlfn.XLOOKUP(1, (prices!$A:$A=$A12)*(prices!$C:$C=DATEVALUE("2024-04-30")), prices!$B:$B))-1} -> 0.075082788 | G12: {=(_xlfn.XLOOKUP(1, (prices!$A:$A=$A12)*(prices!$C:$C=DATEVALUE("2024-06-30")), prices!$B:$B)/_xlfn.XLOOKUP(1, (prices!$A:$A=$A12)*(prices!$C:$C=DATEVALUE("2024-05-31")), prices!$B:$B))-1} -> 0.17377193 | H12: {=(_xlfn.XLOOKUP(1, (prices!$A:$A=$A12)*(prices!$C:$C=DATEVALUE("2024-07-31")), prices!$B:$B)/_xlfn.XLOOKUP(1, (prices!$A:$A=$A12)*(prices!$C:$C=DATEVALUE("2024-06-30")), prices!$B:$B))-1} -> 0.063987391 | I12: {=(_xlfn.XLOOKUP(1, (prices!$A:$A=$A12)*(prices!$C:$C=DATEVALUE("2024-08-31")), prices!$B:$B)/_xlfn.XLOOKUP(1, (prices!$A:$A=$A12)*(prices!$C:$C=DATEVALUE("2024-07-31")), prices!$B:$B))-1} -> 0.046291733 | J12: {=(_xlfn.XLOOKUP(1, (prices!$A:$A=$A12)*(prices!$C:$C=DATEVALUE("2024-09-30")), prices!$B:$B)/_xlfn.XLOOKUP(1, (prices!$A:$A=$A12)*(prices!$C:$C=DATEVALUE("2024-08-31")), prices!$B:$B))-1} -> 0.089906003 | K12: {=(_xlfn.XLOOKUP(1, (prices!$A:$A=$A12)*(prices!$C:$C=DATEVALUE("2024-10-31")), prices!$B:$B)/_xlfn.XLOOKUP(1, (prices!$A:$A=$A12)*(prices!$C:$C=DATEVALUE("2024-09-30")), prices!$B:$B))-1} -> -0.090103377 | L12: {=(_xlfn.XLOOKUP(1, (prices!$A:$A=$A12)*(prices!$C:$C=DATEVALUE("2024-11-30")), prices!$B:$B)/_xlfn.XLOOKUP(1, (prices!$A:$A=$A12)*(prices!$C:$C=DATEVALUE("2024-10-31")), prices!$B:$B))-1} -> 0.10979289 | M12: {=(_xlfn.XLOOKUP(1, (prices!$A:$A=$A12)*(prices!$C:$C=DATEVALUE("2024-12-31")), prices!$B:$B)/_xlfn.XLOOKUP(1, (prices!$A:$A=$A12)*(prices!$C:$C=DATEVALUE("2024-11-30")), prices!$B:$B))-1} -> -0.02524515
A13: =funds_20231231!A14 -> ZAVKE | B13: {=(_xlfn.XLOOKUP(1, (prices!$A:$A=$A13)*(prices!$C:$C=DATEVALUE("2024-01-31")), prices!$B:$B)/_xlfn.XLOOKUP(1, (prices!$A:$A=$A13)*(prices!$C:$C=DATE(2023,12,31)), prices!$B:$B))-1} -> 0.054990426 | C13: {=(_xlfn.XLOOKUP(1, (prices!$A:$A=$A13)*(prices!$C:$C=DATEVALUE("2024-02-29")), prices!$B:$B)/_xlfn.XLOOKUP(1, (prices!$A:$A=$A13)*(prices!$C:$C=DATEVALUE("2024-01-31")), prices!$B:$B))-1} -> -0.054812187 | D13: {=(_xlfn.XLOOKUP(1, (prices!$A:$A=$A13)*(prices!$C:$C=DATEVALUE("2024-03-31")), prices!$B:$B)/_xlfn.XLOOKUP(1, (prices!$A:$A=$A13)*(prices!$C:$C=DATEVALUE("2024-02-29")), prices!$B:$B))-1} -> 0.041191955 | E13: {=(_xlfn.XLOOKUP(1, (prices!$A:$A=$A13)*(prices!$C:$C=DATEVALUE("2024-04-30")), prices!$B:$B)/_xlfn.XLOOKUP(1, (prices!$A:$A=$A13)*(prices!$C:$C=DATEVALUE("2024-03-31")), prices!$B:$B))-1} -> 0.0033540962 | F13: {=(_xlfn.XLOOKUP(1, (prices!$A:$A=$A13)*(prices!$C:$C=DATEVALUE("2024-05-31")), prices!$B:$B)/_xlfn.XLOOKUP(1, (prices!$A:$A=$A13)*(prices!$C:$C=DATEVALUE("2024-04-30")), prices!$B:$B))-1} -> -0.031264006 | G13: {=(_xlfn.XLOOKUP(1, (prices!$A:$A=$A13)*(prices!$C:$C=DATEVALUE("2024-06-30")), prices!$B:$B)/_xlfn.XLOOKUP(1, (prices!$A:$A=$A13)*(prices!$C:$C=DATEVALUE("2024-05-31")), prices!$B:$B))-1} -> 0.075358321 | H13: {=(_xlfn.XLOOKUP(1, (prices!$A:$A=$A13)*(prices!$C:$C=DATEVALUE("2024-07-31")), prices!$B:$B)/_xlfn.XLOOKUP(1, (prices!$A:$A=$A13)*(prices!$C:$C=DATEVALUE("2024-06-30")), prices!$B:$B))-1} -> 0.080538882 | I13: {=(_xlfn.XLOOKUP(1, (prices!$A:$A=$A13)*(prices!$C:$C=DATEVALUE("2024-08-31")), prices!$B:$B)/_xlfn.XLOOKUP(1, (prices!$A:$A=$A13)*(prices!$C:$C=DATEVALUE("2024-07-31")), prices!$B:$B))-1} -> 0.10233091 | J13: {=(_xlfn.XLOOKUP(1, (prices!$A:$A=$A13)*(prices!$C:$C=DATEVALUE("2024-09-30")), prices!$B:$B)/_xlfn.XLOOKUP(1, (prices!$A:$A=$A13)*(prices!$C:$C=DATEVALUE("2024-08-31")), prices!$B:$B))-1} -> 0.061718647 | K13: {=(_xlfn.XLOOKUP(1, (prices!$A:$A=$A13)*(prices!$C:$C=DATEVALUE("2024-10-31")), prices!$B:$B)/_xlfn.XLOOKUP(1, (prices!$A:$A=$A13)*(prices!$C:$C=DATEVALUE("2024-09-30")), prices!$B:$B))-1} -> -0.0071624424 | L13: {=(_xlfn.XLOOKUP(1, (prices!$A:$A=$A13)*(prices!$C:$C=DATEVALUE("2024-11-30")), prices!$B:$B)/_xlfn.XLOOKUP(1, (prices!$A:$A=$A13)*(prices!$C:$C=DATEVALUE("2024-10-31")), prices!$B:$B))-1} -> -0.037030588 | M13: {=(_xlfn.XLOOKUP(1, (prices!$A:$A=$A13)*(prices!$C:$C=DATEVALUE("2024-12-31")), prices!$B:$B)/_xlfn.XLOOKUP(1, (prices!$A:$A=$A13)*(prices!$C:$C=DATEVALUE("2024-11-30")), prices!$B:$B))-1} -> -0.059988858
... A47: =funds_20231231!A48 -> ZAARI | B47: {=(_xlfn.XLOOKUP(1, (prices!$A:$A=$A47)*(prices!$C:$C=DATEVALUE("2024-01-31")), prices!$B:$B)/_xlfn.XLOOKUP(1, (prices!$A:$A=$A47)*(prices!$C:$C=DATE(2023,12,31)), prices!$B:$B))-1} -> -0.088120035 | C47: {=(_xlfn.XLOOKUP(1, (prices!$A:$A=$A47)*(prices!$C:$C=DATEVALUE("2024-02-29")), prices!$B:$B)/_xlfn.XLOOKUP(1, (prices!$A:$A=$A47)*(prices!$C:$C=DATEVALUE("2024-01-31")), prices!$B:$B))-1} -> -0.11747197 | D47: {=(_xlfn.XLOOKUP(1, (prices!$A:$A=$A47)*(prices!$C:$C=DATEVALUE("2024-03-31")), prices!$B:$B)/_xlfn.XLOOKUP(1, (prices!$A:$A=$A47)*(prices!$C:$C=DATEVALUE("2024-02-29")), prices!$B:$B))-1} -> -0.013090609 | E47: {=(_xlfn.XLOOKUP(1, (prices!$A:$A=$A47)*(prices!$C:$C=DATEVALUE("2024-04-30")), prices!$B:$B)/_xlfn.XLOOKUP(1, (prices!$A:$A=$A47)*(prices!$C:$C=DATEVALUE("2024-03-31")), prices!$B:$B))-1} -> 0.19946562 | F47: {=(_xlfn.XLOOKUP(1, (prices!$A:$A=$A47)*(prices!$C:$C=DATEVALUE("2024-05-31")), prices!$B:$B)/_xlfn.XLOOKUP(1, (prices!$A:$A=$A47)*(prices!$C:$C=DATEVALUE("2024-04-30")), prices!$B:$B))-1} -> 0.15133388 | G47: {=(_xlfn.XLOOKUP(1, (prices!$A:$A=$A47)*(prices!$C:$C=DATEVALUE("2024-06-30")), prices!$B:$B)/_xlfn.XLOOKUP(1, (prices!$A:$A=$A47)*(prices!$C:$C=DATEVALUE("2024-05-31")), prices!$B:$B))-1} -> 0.036374873 | H47: {=(_xlfn.XLOOKUP(1, (prices!$A:$A=$A47)*(prices!$C:$C=DATEVALUE("2024-07-31")), prices!$B:$B)/_xlfn.XLOOKUP(1, (prices!$A:$A=$A47)*(prices!$C:$C=DATEVALUE("2024-06-30")), prices!$B:$B))-1} -> -0.044861998 | I47: {=(_xlfn.XLOOKUP(1, (prices!$A:$A=$A47)*(prices!$C:$C=DATEVALUE("2024-08-31")), prices!$B:$B)/_xlfn.XLOOKUP(1, (prices!$A:$A=$A47)*(prices!$C:$C=DATEVALUE("2024-07-31")), prices!$B:$B))-1} -> -0.17465151 | J47: {=(_xlfn.XLOOKUP(1, (prices!$A:$A=$A47)*(prices!$C:$C=DATEVALUE("2024-09-30")), prices!$B:$B)/_xlfn.XLOOKUP(1, (prices!$A:$A=$A47)*(prices!$C:$C=DATEVALUE("2024-08-31")), prices!$B:$B))-1} -> 0.12127306 | K47: {=(_xlfn.XLOOKUP(1, (prices!$A:$A=$A47)*(prices!$C:$C=DATEVALUE("2024-10-31")), prices!$B:$B)/_xlfn.XLOOKUP(1, (prices!$A:$A=$A47)*(prices!$C:$C=DATEVALUE("2024-09-30")), prices!$B:$B))-1} -> -0.08589457 | L47: {=(_xlfn.XLOOKUP(1, (prices!$A:$A=$A47)*(prices!$C:$C=DATEVALUE("2024-11-30")), prices!$B:$B)/_xlfn.XLOOKUP(1, (prices!$A:$A=$A47)*(prices!$C:$C=DATEVALUE("2024-10-31")), prices!$B:$B))-1} -> -0.12358947 | M47: {=(_xlfn.XLOOKUP(1, (prices!$A:$A=$A47)*(prices!$C:$C=DATEVALUE("2024-12-31")), prices!$B:$B)/_xlfn.XLOOKUP(1, (prices!$A:$A=$A47)*(prices!$C:$C=DATEVALUE("2024-11-30")), prices!$B:$B))-1} -> -0.094677688

Sheet 3_performance
A1: Metric | B1: Portfolio | C1: Benchmark | D1: Alpha
A2: Annual Returns | B2: =SUMPRODUCT('1_marketValue'!E2:E47,'1_marketValue'!F2:F47) -> 0.10309356 | C2: =SUMPRODUCT(Table1[Weight],Table1[Return]) -> 0.081356345 | D2: =B2-C2 -> 0.021737218

Sheet updatedBenchmark
A1: Asset | B1: Holdings | C1: Price | D1: MV | E1: Weight | F1: Return | G1: Category
A2: ZAPAN | B2: 2.8308205e+08 | C2: {=_xlfn.XLOOKUP(1, (prices!$A:$A=A2)*(prices!$C:$C=DATE(2023,12,31)), prices!$B:$B)} -> 0.22365003 | D2: =B2*C2 -> 63311310 | E2: =D2/$D$78 -> 0.00015903823 | F2: {=(_xlfn.XLOOKUP(1, (prices!$A:$A=A2)*(prices!$C:$C=DATE(2024,12,31)), prices!$B:$B)/_xlfn.XLOOKUP(1, (prices!$A:$A=A2)*(prices!$C:$C=DATE(2023,12,31)), prices!$B:$B))-1} -> 0.9406313 | G2: =_xlfn.XLOOKUP(A2, attributes!A:A, attributes!C:C) -> Resources
A3: ZAMNP | B3: 1.5791355e+08 | C3: {=_xlfn.XLOOKUP(1, (prices!$A:$A=A3)*(prices!$C:$C=DATE(2023,12,31)), prices!$B:$B)} -> 19.849624 | D3: =B3*C3 -> 3.1345245e+09 | E3: =D3/$D$78 -> 0.0078739366 | F3: {=(_xlfn.XLOOKUP(1, (prices!$A:$A=A3)*(prices!$C:$C=DATE(2024,12,31)), prices!$B:$B)/_xlfn.XLOOKUP(1, (prices!$A:$A=A3)*(prices!$C:$C=DATE(2023,12,31)), prices!$B:$B))-1} -> -0.25913547 | G3: =_xlfn.XLOOKUP(A3, attributes!A:A, attributes!C:C) -> Rand Sensitives
A4: ZABTI | B4: 3.0389436e+08 | C4: {=_xlfn.XLOOKUP(1, (prices!$A:$A=A4)*(prices!$C:$C=DATE(2023,12,31)), prices!$B:$B)} -> 29.610936 | D4: =B4*C4 -> 8.9985965e+09 | E4: =D4/$D$78 -> 0.022604506 | F4: {=(_xlfn.XLOOKUP(1, (prices!$A:$A=A4)*(prices!$C:$C=DATE(2024,12,31)), prices!$B:$B)/_xlfn.XLOOKUP(1, (prices!$A:$A=A4)*(prices!$C:$C=DATE(2023,12,31)), prices!$B:$B))-1} -> 0.2108454 | G4: =_xlfn.XLOOKUP(A4, attributes!A:A, attributes!C:C) -> Rand Sensitives
A5: ZAINP | B5: 3.4504301e+08 | C5: {=_xlfn.XLOOKUP(1, (prices!$A:$A=A5)*(prices!$C:$C=DATE(2023,12,31)), prices!$B:$B)} -> 6.887218 | D5: =B5*C5 -> 2.3763864e+09 | E5: =D5/$D$78 -> 0.0059694911 | F5: {=(_xlfn.XLOOKUP(1, (prices!$A:$A=A5)*(prices!$C:$C=DATE(2024,12,31)), prices!$B:$B)/_xlfn.XLOOKUP(1, (prices!$A:$A=A5)*(prices!$C:$C=DATE(2023,12,31)), prices!$B:$B))-1} -> -0.025098178 | G5: =_xlfn.XLOOKUP(A5, attributes!A:A, attributes!C:C) -> Rand Sensitives
A6: ZACFR | B6: 1148400000 | C6: {=_xlfn.XLOOKUP(1, (prices!$A:$A=A6)*(prices!$C:$C=DATE(2023,12,31)), prices!$B:$B)} -> 140.40246 | D6: =B6*C6 -> 1.6123819e+11 | E6: =D6/$D$78 -> 0.40503089 | F6: {=(_xlfn.XLOOKUP(1, (prices!$A:$A=A6)*(prices!$C:$C=DATE(2024,12,31)), prices!$B:$B)/_xlfn.XLOOKUP(1, (prices!$A:$A=A6)*(prices!$C:$C=DATE(2023,12,31)), prices!$B:$B))-1} -> 0.047748861 | G6: =_xlfn.XLOOKUP(A6, attributes!A:A, attributes!C:C) -> Rand Sensitives
A7: ZAATT | B7: 3.6881762e+08 | C7: {=_xlfn.XLOOKUP(1, (prices!$A:$A=A7)*(prices!$C:$C=DATE(2023,12,31)), prices!$B:$B)} -> 0.50416951 | D7: =B7*C7 -> 1.859466e+08 | E7: =D7/$D$78 -> 0.00046709851 | F7: {=(_xlfn.XLOOKUP(1, (prices!$A:$A=A7)*(prices!$C:$C=DATE(2024,12,31)), prices!$B:$B)/_xlfn.XLOOKUP(1, (prices!$A:$A=A7)*(prices!$C:$C=DATE(2023,12,31)), prices!$B:$B))-1} -> 0.45790082 | G7: =_xlfn.XLOOKUP(A7, attributes!A:A, attributes!C:C) -> Property
A8: ZACOH | B8: 56010934 | C8: {=_xlfn.XLOOKUP(1, (prices!$A:$A=A8)*(prices!$C:$C=DATE(2023,12,31)), prices!$B:$B)} -> 0.63704716 | D8: =B8*C8 -> 35681607 | E8: =D8/$D$78 -> 8.9632321e-05 | F8: {=(_xlfn.XLOOKUP(1, (prices!$A:$A=A8)*(prices!$C:$C=DATE(2024,12,31)), prices!$B:$B)/_xlfn.XLOOKUP(1, (prices!$A:$A=A8)*(prices!$C:$C=DATE(2023,12,31)), prices!$B:$B))-1} -> 0.085592977 | G8: =_xlfn.XLOOKUP(A8, attributes!A:A, attributes!C:C) -> SA Inc
A9: ZAAGL | B9: 7.0272747e+08 | C9: {=_xlfn.XLOOKUP(1, (prices!$A:$A=A9)*(prices!$C:$C=DATE(2023,12,31)), prices!$B:$B)} -> 25.891456 | D9: =B9*C9 -> 1.8194637e+10 | E9: =D9/$D$78 -> 0.045704992 | F9: {=(_xlfn.XLOOKUP(1, (prices!$A:$A=A9)*(prices!$C:$C=DATE(2024,12,31)), prices!$B:$B)/_xlfn.XLOOKUP(1, (prices!$A:$A=A9)*(prices!$C:$C=DATE(2023,12,31)), prices!$B:$B))-1} -> 0.12951675 | G9: =_xlfn.XLOOKUP(A9, attributes!A:A, attributes!C:C) -> Resources
A10: ZALHC | B10: 917144580 | C10: {=_xlfn.XLOOKUP(1, (prices!$A:$A=A10)*(prices!$C:$C=DATE(2023,12,31)), prices!$B:$B)} -> 1.0045113 | D10: =B10*C10 -> 9.2128207e+08 | E10: =D10/$D$78 -> 0.0023142638 | F10: {=(_xlfn.XLOOKUP(1, (prices!$A:$A=A10)*(prices!$C:$C=DATE(2024,12,31)), prices!$B:$B)/_xlfn.XLOOKUP(1, (prices!$A:$A=A10)*(prices!$C:$C=DATE(2023,12,31)), prices!$B:$B))-1} -> -0.13585389 | G10: =_xlfn.XLOOKUP(A10, attributes!A:A, attributes!C:C) -> SA Inc
A11: ZAVOD | B11: 327349880 | C11: {=_xlfn.XLOOKUP(1, (prices!$A:$A=A11)*(prices!$C:$C=DATE(2023,12,31)), prices!$B:$B)} -> 5.796309 | D11: =B11*C11 -> 1.897421e+09 | E11: =D11/$D$78 -> 0.0047663283 | F11: {=(_xlfn.XLOOKUP(1, (prices!$A:$A=A11)*(prices!$C:$C=DATE(2024,12,31)), prices!$B:$B)/_xlfn.XLOOKUP(1, (prices!$A:$A=A11)*(prices!$C:$C=DATE(2023,12,31)), prices!$B:$B))-1} -> -0.073291438 | G11: =_xlfn.XLOOKUP(A11, attributes!A:A, attributes!C:C) -> SA Inc
A12: ZAAIP | B12: 1.4810124e+08 | C12: {=_xlfn.XLOOKUP(1, (prices!$A:$A=A12)*(prices!$C:$C=DATE(2023,12,31)), prices!$B:$B)} -> 3.2863978 | D12: =B12*C12 -> 4.8671959e+08 | E12: =D12/$D$78 -> 0.0012226413 | F12: {=(_xlfn.XLOOKUP(1, (prices!$A:$A=A12)*(prices!$C:$C=DATE(2024,12,31)), prices!$B:$B)/_xlfn.XLOOKUP(1, (prices!$A:$A=A12)*(prices!$C:$C=DATE(2023,12,31)), prices!$B:$B))-1} -> 0.080395508 | G12: =_xlfn.XLOOKUP(A12, attributes!A:A, attributes!C:C) -> SA Inc
A13: ZABLU | B13: 3.7097997e+08 | C13: {=_xlfn.XLOOKUP(1, (prices!$A:$A=A13)*(prices!$C:$C=DATE(2023,12,31)), prices!$B:$B)} -> 0.21216678 | D13: =B13*C13 -> 78709627 | E13: =D13/$D$78 -> 0.00019771886 | F13: {=(_xlfn.XLOOKUP(1, (prices!$A:$A=A13)*(prices!$C:$C=DATE(2024,12,31)), prices!$B:$B)/_xlfn.XLOOKUP(1, (prices!$A:$A=A13)*(prices!$C:$C=DATE(2023,12,31)), prices!$B:$B))-1} -> 0.45869186 | G13: =_xlfn.XLOOKUP(A13, attributes!A:A, attributes!C:C) -> SA Inc
... A77: ZAARI | B77: 77579841 | C77: {=_xlfn.XLOOKUP(1, (prices!$A:$A=A77)*(prices!$C:$C=DATE(2023,12,31)), prices!$B:$B)} -> 10.936432 | D77: =B77*C77 -> 8.4844666e+08 | E77: =D77/$D$78 -> 0.002131301 | F77: {=(_xlfn.XLOOKUP(1, (prices!$A:$A=A77)*(prices!$C:$C=DATE(2024,12,31)), prices!$B:$B)/_xlfn.XLOOKUP(1, (prices!$A:$A=A77)*(prices!$C:$C=DATE(2023,12,31)), prices!$B:$B))-1} -> -0.27126202 | G77: =_xlfn.XLOOKUP(A77, attributes!A:A, attributes!C:C) -> Resources
D78: =SUM(Table1[MV]) -> 3.9808862e+11

Sheet 4_brinsonAttribution
A1: Category | B1: w_p | C1: w_b | D1: r_p | E1: r_b | F1: Allocation | G1: Selection | H1: Interaction | I1: Total
A2: Property | B2: =SUMIF('1_marketValue'!G:G, A2, '1_marketValue'!E:E) -> 0.005254675 | C2: =SUMIF(Table1[Category],'4_brinsonAttribution'!A2,Table1[Weight]) -> 0.0092532586 | D2: {=IF(B2=0,0,SUMPRODUCT(--('1_marketValue'!B2:B47),'1_marketValue'!E2:E47,'1_marketValue'!F2:F47)/'4_brinsonAttribution'!B2)} -> 2097521.9 | E2: 0.2063 | F2: =(B2-C2)*E2 -> -0.00082490781 | G2: =C2*(D2-E2) -> 19408.91 | H2: =(B2-C2)*(D2-E2) -> -8387.1158 | I2: =SUM(F2:H2) -> 11021.794
A3: Rand Sensitives | B3: =SUMIF('1_marketValue'!G:G, A3, '1_marketValue'!E:E) -> 0.27790315 | C3: =SUMIF(Table1[Category],'4_brinsonAttribution'!A3,Table1[Weight]) -> 0.61777108 | D3: {=IF(B3=0,0,SUMPRODUCT(--('1_marketValue'!B3:B48),'1_marketValue'!E3:E48,'1_marketValue'!F3:F48)/'4_brinsonAttribution'!B3)} -> 45320.353 | E3: 0.1156 | F3: =(B3-C3)*E3 -> -0.039288733 | G3: =C3*(D3-E3) -> 27997.532 | H3: =(B3-C3)*(D3-E3) -> -15402.895 | I3: =SUM(F3:H3) -> 12594.597
A4: Resources | B4: =SUMIF('1_marketValue'!G:G, A4, '1_marketValue'!E:E) -> 0.35205632 | C4: =SUMIF(Table1[Category],'4_brinsonAttribution'!A4,Table1[Weight]) -> 0.11826628 | D4: {=IF(B4=0,0,SUMPRODUCT(--('1_marketValue'!B4:B49),'1_marketValue'!E4:E49,'1_marketValue'!F4:F49)/'4_brinsonAttribution'!B4)} -> 33129.574 | E4: -0.0791 | F4: =(B4-C4)*E4 -> -0.018492792 | G4: =C4*(D4-E4) -> 3918.1207 | H4: =(B4-C4)*(D4-E4) -> 7745.3829 | I4: =SUM(F4:H4) -> 11663.485
A5: SA Inc | B5: =SUMIF('1_marketValue'!G:G, A5, '1_marketValue'!E:E) -> 0.36478586 | C5: =SUMIF(Table1[Category],'4_brinsonAttribution'!A5,Table1[Weight]) -> 0.25470938 | D5: {=IF(B5=0,0,SUMPRODUCT(--('1_marketValue'!B5:B50),'1_marketValue'!E5:E50,'1_marketValue'!F5:F50)/'4_brinsonAttribution'!B5)} -> 32391.885 | E5: 0.0684 | F5: =(B5-C5)*E5 -> 0.0075292307 | G5: =C5*(D5-E5) -> 8250.4995 | H5: =(B5-C5)*(D5-E5) -> 3565.5769 | I5: =SUM(F5:H5) -> 11816.084
